{"languages": ["es", "ca"], "name_es": "Explorador de Igualdades", "banner_es": "equality-explorer.png", "html_es": "equality-explorer_es.html", "name_ca": "Equality Explorer", "banner_ca": "equality-explorer.png", "html_ca": "equality-explorer_ca.html", "category": "math", "require": "", "license": "GNU General Public License v3.0", "url": "https://github.com/phetsims/equality-explorer", "description": "\"Equality Explorer\" is an educational simulation in HTML5, by PhET Interactive Simulations."}